whitemagic/__init__.py
whitemagic/auto_tagger.py
whitemagic/backup.py
whitemagic/cache.py
whitemagic/chinese_dict.py
whitemagic/cli_app.py
whitemagic/cli_graph.py
whitemagic/cli_relationships.py
whitemagic/cli_templates.py
whitemagic/concept_map.py
whitemagic/constants.py
whitemagic/core.py
whitemagic/delta_tracking.py
whitemagic/exceptions.py
whitemagic/fileio.py
whitemagic/lifecycle.py
whitemagic/metrics.py
whitemagic/models.py
whitemagic/optimized_context.py
whitemagic/py.typed
whitemagic/relationships.py
whitemagic/session_templates.py
whitemagic/session_types.py
whitemagic/smart_read.py
whitemagic/stats.py
whitemagic/strategy.py
whitemagic/summaries.py
whitemagic/symbolic.py
whitemagic/symbolic_memory.py
whitemagic/threading_tiers.py
whitemagic/utils.py
whitemagic/workflow_patterns.py
whitemagic/workspace_loader.py
whitemagic/wu_xing.py
whitemagic/api/__init__.py
whitemagic/api/app.py
whitemagic/api/auth.py
whitemagic/api/database.py
whitemagic/api/dependencies.py
whitemagic/api/logging_config.py
whitemagic/api/memory_service.py
whitemagic/api/middleware.py
whitemagic/api/models.py
whitemagic/api/rate_limit.py
whitemagic/api/structured_logging.py
whitemagic/api/version.py
whitemagic/api/routes/__init__.py
whitemagic/api/routes/api_keys.py
whitemagic/api/routes/dashboard.py
whitemagic/api/routes/exec.py
whitemagic/api/routes/search.py
whitemagic/cli/__init__.py
whitemagic/cli/exec.py
whitemagic/config/__init__.py
whitemagic/config/manager.py
whitemagic/config/schema.py
whitemagic/embeddings/__init__.py
whitemagic/embeddings/base.py
whitemagic/embeddings/config.py
whitemagic/embeddings/local_provider.py
whitemagic/embeddings/openai_provider.py
whitemagic/embeddings/storage.py
whitemagic/parallel/__init__.py
whitemagic/parallel/adaptive.py
whitemagic/parallel/cache.py
whitemagic/parallel/file_ops.py
whitemagic/parallel/memory_ops.py
whitemagic/parallel/pipeline.py
whitemagic/parallel/pools.py
whitemagic/parallel/scheduler.py
whitemagic/scratchpad/__init__.py
whitemagic-2.2.7.dist-info/licenses/LICENSE
whitemagic-2.2.7.dist-info/METADATA
whitemagic-2.2.7.dist-info/WHEEL
whitemagic-2.2.7.dist-info/entry_points.txt
whitemagic-2.2.7.dist-info/top_level.txt
whitemagic-2.2.7.dist-info/RECORD
