Metadata-Version: 2.4
Name: whitemagic
Version: 2.2.7
Summary: Tiered memory management system for AI agents with native MCP support
Author: WhiteMagic Contributors
License: MIT
Project-URL: Homepage, https://github.com/lbailey94/whitemagic
Project-URL: Documentation, https://github.com/lbailey94/whitemagic#readme
Project-URL: Repository, https://github.com/lbailey94/whitemagic
Project-URL: Bug Tracker, https://github.com/lbailey94/whitemagic/issues
Keywords: memory,ai,mcp,context,llm,agents
Classifier: Development Status :: 4 - Beta
Classifier: Intended Audience :: Developers
Classifier: License :: OSI Approved :: MIT License
Classifier: Programming Language :: Python :: 3
Classifier: Programming Language :: Python :: 3.10
Classifier: Programming Language :: Python :: 3.11
Classifier: Programming Language :: Python :: 3.12
Classifier: Topic :: Software Development :: Libraries :: Python Modules
Classifier: Topic :: Scientific/Engineering :: Artificial Intelligence
Requires-Python: >=3.10
License-File: LICENSE
Requires-Dist: pydantic>=2.0.0
Requires-Dist: pydantic-settings>=2.1.0
Requires-Dist: email-validator>=2.0.0
Requires-Dist: fastapi>=0.104.0
Requires-Dist: uvicorn[standard]>=0.24.0
Requires-Dist: python-multipart>=0.0.6
Requires-Dist: sqlalchemy>=2.0.0
Requires-Dist: aiosqlite>=0.19.0
Requires-Dist: asyncpg>=0.29.0
Requires-Dist: alembic>=1.13.0
Requires-Dist: redis>=5.0.1
Requires-Dist: httpx>=0.25.0
Requires-Dist: requests>=2.31.0
Requires-Dist: urllib3<3.0.0,>=2.0.0
Requires-Dist: chardet>=5.0.0
Requires-Dist: openai>=1.3.0
Requires-Dist: numpy>=1.24.0
Requires-Dist: python-json-logger>=2.0.7
Requires-Dist: pyyaml>=6.0.0
Requires-Dist: rich>=13.0.0
Requires-Dist: python-jose[cryptography]>=3.3.0
Requires-Dist: passlib[bcrypt]>=1.7.4
Provides-Extra: embeddings
Requires-Dist: sentence-transformers>=2.2.0; extra == "embeddings"
Requires-Dist: torch>=2.0.0; extra == "embeddings"
Requires-Dist: scipy>=1.10.0; extra == "embeddings"
Provides-Extra: terminal
Provides-Extra: offline
Requires-Dist: sentence-transformers>=2.2.0; extra == "offline"
Requires-Dist: torch>=2.0.0; extra == "offline"
Requires-Dist: scipy>=1.10.0; extra == "offline"
Provides-Extra: dev
Requires-Dist: pytest>=7.0.0; extra == "dev"
Requires-Dist: pytest-asyncio>=0.21.0; extra == "dev"
Requires-Dist: pytest-cov>=4.1.0; extra == "dev"
Requires-Dist: black>=23.0.0; extra == "dev"
Requires-Dist: mypy>=1.0.0; extra == "dev"
Requires-Dist: ruff>=0.1.6; extra == "dev"
Provides-Extra: api
Dynamic: license-file
